dynamic_data_set/__init__.py
dynamic_data_set/__main__.py
dynamic_data_set/cli.py
dynamic_data_set/converter.py
dynamic_data_set/formatter.py
dynamic_data_set-0.1.0.dist-info/METADATA
dynamic_data_set-0.1.0.dist-info/WHEEL
dynamic_data_set-0.1.0.dist-info/entry_points.txt
dynamic_data_set-0.1.0.dist-info/licenses/LICENSE
dynamic_data_set-0.1.0.dist-info/RECORD
