Metadata-Version: 2.4
Name: dynamic-data-set
Version: 0.1.0
Summary: A CLI tool to convert CSV files to Parquet format, Parquet files to CSV, and display formatted content of data files.
Project-URL: Homepage, https://github.com/Wenrh2004/dynamic-data-set
Project-URL: Repository, https://github.com/Wenrh2004/dynamic-data-set
Project-URL: Documentation, https://github.com/Wenrh2004/dynamic-data-set#readme
Project-URL: Bug Reports, https://github.com/Wenrh2004/dynamic-data-set/issues
Author-email: "KingYen." <1696918097@qq.com>
Maintainer-email: "KingYen." <1696918097@qq.com>
License: The MIT License (MIT)
License-File: LICENSE
Keywords: cli,conversion,csv,data,parquet
Classifier: Development Status :: 4 - Beta
Classifier: Environment :: Console
Classifier: Intended Audience :: Developers
Classifier: Intended Audience :: End Users/Desktop
Classifier: License :: OSI Approved :: MIT License
Classifier: Operating System :: OS Independent
Classifier: Programming Language :: Python :: 3
Classifier: Programming Language :: Python :: 3.10
Classifier: Programming Language :: Python :: 3.11
Classifier: Programming Language :: Python :: 3.12
Classifier: Topic :: Software Development :: Libraries :: Python Modules
Classifier: Topic :: Utilities
Requires-Python: >=3.10
Requires-Dist: pandas>=2.0.0
Requires-Dist: typer>=0.9.0
Provides-Extra: dev
Requires-Dist: pre-commit>=3.0.0; extra == 'dev'
Requires-Dist: pytest-cov>=4.0.0; extra == 'dev'
Requires-Dist: pytest>=7.0.0; extra == 'dev'
Provides-Extra: test
Requires-Dist: pytest-cov>=4.0.0; extra == 'test'
Requires-Dist: pytest>=7.0.0; extra == 'test'
